[{
        "title": "湖南",
        "code": "43232332",
        "nodes": [{
                "title": "益阳",
                "code": "432423",
                "nodes": [
                    {
                        "title": "桃江",
                        "code": "4324236565",
                        "nodes": [{
                            "title": "高桥",
                            "code": "432423656576",
                            "node": []
                        }]
                    },
                    {
                        "title": "安化",
                        "code": "432423343",
                        "nodes": []
                    }
                ]
            },
            {
                "title": "长沙",
                "code": "43252324",
                "node": []
            },
            {
                "title": "郴州",
                "code": "434343",
                "node": []
            }
        ]
    },
    {
        "title": "广州",
        "code": "5324324",
        "nodes": [{
                "title": "深圳",
                "code": "53343423",
                "node": [{
                        "title": "宝安",
                        "code": "53343423344",
                        "nodes": []
                    },
                    {
                        "title": "南山",
                        "code": "5334342376565",
                        "nodes": []
                    }
                ]
            },
            {
                "title": "顺德",
                "code": "535233",
                "node": []
            },
            {
                "title": "潮汕",
                "code": "5352343",
                "node": []
            }
        ]
    },
    {
        "title": "香港",
        "code": "7543534",
        "nodes": []
    },
    {
        "title": "云南",
        "code": "64543",
        "nodes": [{
                "title": "昆明",
                "code": "64346",
                "node": []
            },
            {
                "title": "大理",
                "code": "7665454",
                "node": []
            },
            {
                "title": "丽江",
                "code": "6463454",
                "node": []
            }
        ]
    }
]